qctrlvisualizer/__init__.py
qctrlvisualizer/bloch.py
qctrlvisualizer/confidence_ellipses.py
qctrlvisualizer/controls.py
qctrlvisualizer/cost_histories.py
qctrlvisualizer/density_matrix.py
qctrlvisualizer/filter_functions.py
qctrlvisualizer/histogram.py
qctrlvisualizer/populations.py
qctrlvisualizer/style.py
qctrlvisualizer/utils.py
qctrlvisualizer/wigner_function.py
qctrl_visualizer-10.0.0.dist-info/LICENSE
qctrl_visualizer-10.0.0.dist-info/METADATA
qctrl_visualizer-10.0.0.dist-info/WHEEL
qctrl_visualizer-10.0.0.dist-info/RECORD
